pulses/__init__.py
pulses/cli.py
pulses/cli_parser.py
pulses/methods.py
pulses/pulses.py
pulses-1.0.2.dist-info/LICENSE
pulses-1.0.2.dist-info/METADATA
pulses-1.0.2.dist-info/WHEEL
pulses-1.0.2.dist-info/entry_points.txt
pulses-1.0.2.dist-info/RECORD
