Metadata-Version: 2.1
Name: pulses
Version: 1.0.2
Summary: Pulse LEDs on RPi
Author: Andrea Mistrali
Author-email: andrea@mistrali.pw
Requires-Python: >=3.9,<4.0
Classifier: Programming Language :: Python :: 3
Classifier: Programming Language :: Python :: 3.9
Classifier: Programming Language :: Python :: 3.10
Classifier: Programming Language :: Python :: 3.11
Classifier: Programming Language :: Python :: 3.12
Requires-Dist: rpi-gpio (>=0.7.1,<0.8.0) ; sys_platform == "linux"
